mux2x1.v
module mux2x1 (
  input [1:0] in0,
  input [1:0] in1,
  input sel,
  output [1:0] out
);
  assign out = sel ? in1 : in0;
endmodule

alu.v
module alu (
  input [1:0] a,
  input [1:0] b,
  input sel,             // 0: ADD, 1: SUB
  output reg [1:0] result
);
  always @(*) begin
    case (sel)
      1'b0: result = a + b;
      1'b1: result = a - b;
    endcase
  end
endmodule

counter.v
module counter (
  input clk,
  input rst,
  output reg [3:0] count
);
  always @(posedge clk) begin
    if (rst)
      count <= 0;
    else
      count <= count + 1;
  end
endmodule

mini_soc.v
module mini_soc (
  input clk,
  input rst,
  input alu_sel,
  input mux_sel,
  output [1:0] soc_out
);
  wire [3:0] count;
  wire [1:0] alu_out;
  // Instantiate IP blocks
  counter u_counter (.clk(clk), .rst(rst), .count(count));
  alu     u_alu (.a(count[3:2]), .b(count[1:0]), .sel(alu_sel), .result(alu_out));
  mux2x1  u_mux (.in0(count[3:2]), .in1(alu_out), .sel(mux_sel), .out(soc_out));
endmodule

mini_soc_tb.v
module mini_soc_tb;
  reg clk = 0;
  reg rst = 1;
  reg alu_sel = 0;
  reg mux_sel = 0;
  wire [1:0] soc_out;
  always #5 clk = ~clk;
  mini_soc dut (
    .clk(clk),
    .rst(rst),
    .alu_sel(alu_sel),
    .mux_sel(mux_sel),
    .soc_out(soc_out)
  );
  initial begin
    $dumpfile("dump.vcd");
    $dumpvars(0, mini_soc_tb);
    // Reset release
    #10 rst = 0;
    // Stimulate ALU and MUX selections
    #20 alu_sel = 1;
    #30 mux_sel = 1;
    #40 alu_sel = 0;
    #20 mux_sel = 0;
    #50 $finish;
  end
endmodule

obj_dir/dump.vcd
$version Generated by VerilatedVcd $end
$timescale 1ps $end

 $scope module TOP $end
  $scope module mini_soc_tb $end
   $var wire  1 ( alu_sel $end
   $var wire  1 & clk $end
   $var wire  1 ) mux_sel $end
   $var wire  1 ' rst $end
   $var wire  2 * soc_out [1:0] $end
   $scope module dut $end
    $var wire  2 + alu_out [1:0] $end
    $var wire  1 ( alu_sel $end
    $var wire  1 & clk $end
    $var wire  4 # count [3:0] $end
    $var wire  1 ) mux_sel $end
    $var wire  1 ' rst $end
    $var wire  2 * soc_out [1:0] $end
    $scope module u_alu $end
     $var wire  2 $ a [1:0] $end
     $var wire  2 % b [1:0] $end
     $var wire  2 + result [1:0] $end
     $var wire  1 ( sel $end
    $upscope $end
    $scope module u_counter $end
     $var wire  1 & clk $end
     $var wire  4 # count [3:0] $end
     $var wire  1 ' rst $end
    $upscope $end
    $scope module u_mux $end
     $var wire  2 $ in0 [1:0] $end
     $var wire  2 + in1 [1:0] $end
     $var wire  2 * out [1:0] $end
     $var wire  1 ) sel $end
    $upscope $end
   $upscope $end
  $upscope $end
 $upscope $end
$enddefinitions $end


#0
b0000 #
b00 $
b00 %
0&
1'
0(
0)
b00 *
b00 +
#5
1&
#10
0&
0'
#15
b0001 #
b01 %
1&
b01 +
#20
0&
#25
b0010 #
b10 %
1&
b10 +
#30
0&
1(
#35
b0011 #
b11 %
1&
b01 +
#40
0&
#45
b0100 #
b01 $
b00 %
1&
b01 *
#50
0&
#55
b0101 #
b01 %
1&
b00 +
#60
0&
1)
b00 *
#65
b0110 #
b10 %
1&
b11 *
b11 +
#70
0&
#75
b0111 #
b11 %
1&
b10 *
b10 +
#80
0&
#85
b1000 #
b10 $
b00 %
1&
#90
0&
#95
b1001 #
b01 %
1&
b01 *
b01 +
#100
0&
0(
b11 *
b11 +
#105
b1010 #
b10 %
1&
b00 *
b00 +
#110
0&
#115
b1011 #
b11 %
1&
b01 *
b01 +
#120
0&
0)
b10 *
#125
b1100 #
b11 $
b00 %
1&
b11 *
b11 +
#130
0&
#135
b1101 #
b01 %
1&
b00 +
#140
0&
#145
b1110 #
b10 %
1&
b01 +
#150
0&
#155
b1111 #
b11 %
1&
b10 +
#160
0&
#165
b0000 #
b00 $
b00 %
1&
b00 *
b00 +
